[
    {
        "title": "Ver\u00adga\u00adbe\u00adnum\u00admer: 2518100108, Me\u00adlio\u00adra\u00adti\u00adon und Be\u00adgr\u00fc\u00adnung Ost\u00adsach\u00adsen\nLMBV mbH, Einkauf Lausitz, Knappenstra\u00dfe 1, 01968 \u2026\n05.05.25\n26.05.25",
        "link": "https://www.service.bund.de/IMPORTE/Ausschreibungen/editor/Lausitzer-und-Mitteldeutsche-Bergbau-Verwaltungsgesellschaft-mbH/2025/05/6027045.html;jsessionid=CD71156DCEC286D9D4A6A8D570770280.internet612?nn=4641482&type=0&searchResult=true"
    },
    {
        "title": "DUN, Neu\u00adbau Grund\u00adschu\u00adle, TGA D\u00e4m\u00admung, Eras\u00admus\u00ads\u00adtra\u00ad\u00dfe 11, N\u00fcrn\u00adberg\nStadt N\u00fcrnberg vertreten durch WBG KOMMUNAL GmbH\n05.05.25\n02.06.25",
        "link": "https://www.service.bund.de/IMPORTE/Ausschreibungen/healyhudson/2025/05/ff7118dd-cc81-41a7-8c87-5f22a3636643.html;jsessionid=CD71156DCEC286D9D4A6A8D570770280.internet612?nn=4641482&type=0&searchResult=true"
    },
    {
        "title": "Sch\u00fc\u00adler\u00adbe\u00adf\u00f6r\u00adde\u00adrung von und zu Schu\u00adlen in\u00adner\u00adhalb des Kreis\u00adge\u00adbie\u00adtes des \u2026\nLandkreis Rotenburg (W\u00fcmme)\n05.05.25\n16.05.25",
        "link": "https://www.service.bund.de/IMPORTE/Ausschreibungen/healyhudson/2025/05/fb7a8ba4-fa30-40c4-91f2-1cf39afb8da8.html;jsessionid=CD71156DCEC286D9D4A6A8D570770280.internet612?nn=4641482&type=0&searchResult=true"
    },
    {
        "title": "Ge\u00admein\u00adde Ar\u00adgen\u00adb\u00fchl: Er\u00adsatz\u00adneu\u00adbau Turn- und Fest\u00adhal\u00adle Ei\u00adsen\u00adharz, Sport\u00adge\u00adr\u00e4\u00adte \u2026\nLandratsamt Ravensburg, Zentrale Vergabestelle\n05.05.25\n17.06.25",
        "link": "https://www.service.bund.de/IMPORTE/Ausschreibungen/abc/2025/05/401071G327739.html;jsessionid=CD71156DCEC286D9D4A6A8D570770280.internet612?nn=4641482&type=0&searchResult=true"
    },
    {
        "title": "Uni\u00adver\u00adsal-Mo\u00addul\u00adtr\u00e4\u00adger-Fahr\u00adzeu\u00adge f\u00fcr Ka\u00adta\u00adstro\u00adphen\u00adschutz\nLandesamt f\u00fcr Zentrale Dienste\n05.05.25\n05.06.25",
        "link": "https://www.service.bund.de/IMPORTE/Ausschreibungen/abc/2025/05/401111G327768.html;jsessionid=CD71156DCEC286D9D4A6A8D570770280.internet612?nn=4641482&type=0&searchResult=true"
    },
    {
        "title": "Sa\u00adnie\u00adrung OP-L\u00fcf\u00adtung / Kli\u00adma\u00adti\u00adsie\u00adrung im Miet\u00adbe\u00adreich Pra\u00adxis\u00adkli\u00adnik - RLT\nBG Verkehr Bezirksverwaltung T\u00fcbingen\n05.05.25\n26.05.25",
        "link": "https://www.service.bund.de/IMPORTE/Ausschreibungen/subreport/2025/05/E53664543.html;jsessionid=CD71156DCEC286D9D4A6A8D570770280.internet612?nn=4641482&type=0&searchResult=true"
    },
    {
        "title": "Sa\u00adnie\u00adrung Kli\u00adma?Kalt\u00adwas\u00adser Miet\u00adbe\u00adreich Pra\u00adxis\u00adkli\u00adnik, Aus\u00adtausch von 5 \u2026\nBG Verkehr Bezirksverwaltung T\u00fcbingen\n05.05.25\n26.05.25",
        "link": "https://www.service.bund.de/IMPORTE/Ausschreibungen/subreport/2025/05/E73893956.html;jsessionid=CD71156DCEC286D9D4A6A8D570770280.internet612?nn=4641482&type=0&searchResult=true"
    },
    {
        "title": "Si\u00adcher\u00adheits\u00adan\u00adpas\u00adsung HRB B61 Ton\u00adnen\u00adberg - Ge\u00adwerk 1: Tief- und In\u00adge\u00adnieur\u00adbau\nWasser- und Bodenverband Sechta-Eger\n05.05.25\n04.06.25",
        "link": "https://www.service.bund.de/IMPORTE/Ausschreibungen/subreport/2025/05/E59641351.html;jsessionid=CD71156DCEC286D9D4A6A8D570770280.internet612?nn=4641482&type=0&searchResult=true"
    },
    {
        "title": "Treu\u00adh\u00e4n\u00adde\u00adri\u00adsche Sa\u00adnie\u00adrungs\u00adtr\u00e4\u00adger\u00adleis\u00adtun\u00adgen gem. \u00a7\u00a7 157 ff. BauGB f\u00fcr die \u2026\nStadt Brake(LK Wesermarsch)\n05.05.25\n02.06.25",
        "link": "https://www.service.bund.de/IMPORTE/Ausschreibungen/subreport/2025/05/E14611717.html;jsessionid=CD71156DCEC286D9D4A6A8D570770280.internet612?nn=4641482&type=0&searchResult=true"
    },
    {
        "title": "Soft\u00adwa\u00adre\u00adpfle\u00adge f\u00fcr Check_MK En\u00adter\u00adpri\u00adse\nDeutsches Patent- und Markenamt\n05.05.25\n02.06.25",
        "link": "https://www.service.bund.de/IMPORTE/Ausschreibungen/eVergabe/767779.html;jsessionid=CD71156DCEC286D9D4A6A8D570770280.internet612?nn=4641482&type=0&searchResult=true"
    },
    {
        "title": "Be\u00adra\u00adtung zur E-Rech\u00adnung\nBeschaffungsamt des BMI\n05.05.25\n05.06.25",
        "link": "https://www.service.bund.de/IMPORTE/Ausschreibungen/eVergabe/769989.html;jsessionid=CD71156DCEC286D9D4A6A8D570770280.internet612?nn=4641482&type=0&searchResult=true"
    },
    {
        "title": "KKE 0370.01.05. Tisch\u00adler\u00adar\u00adbei\u00adten Ein\u00adbau\u00adm\u00f6\u00adbel TO2\nTh\u00fcringer Landesamt f\u00fcr Bau und Verkehr, Hochbau \u2026\n05.05.25\n12.06.25",
        "link": "https://www.service.bund.de/IMPORTE/Ausschreibungen/eVergabe/769938.html;jsessionid=CD71156DCEC286D9D4A6A8D570770280.internet612?nn=4641482&type=0&searchResult=true"
    },
    {
        "title": "Neu\u00adge\u00adstal\u00adtung Schul\u00adhof Se\u00adbas\u00adti\u00adan-Kneipp-Schu\u00adle - Sa\u00adnie\u00adrung Ga\u00adra\u00adge und Mau\u00ader\nLandratsamt Unstrut-Hainich-Kreis\n05.05.25\n27.05.25",
        "link": "https://www.service.bund.de/IMPORTE/Ausschreibungen/eVergabe/769106.html;jsessionid=CD71156DCEC286D9D4A6A8D570770280.internet612?nn=4641482&type=0&searchResult=true"
    },
    {
        "title": "REZ NRW 45Unt2 JC Rhein-Sieg\nBundesagentur f\u00fcr Arbeit\n05.05.25\n04.06.25",
        "link": "https://www.service.bund.de/IMPORTE/Ausschreibungen/eVergabe/769954.html;jsessionid=CD71156DCEC286D9D4A6A8D570770280.internet612?nn=4641482&type=0&searchResult=true"
    },
    {
        "title": "REZ NORD 16h JC Kiel\nBundesagentur f\u00fcr Arbeit\n05.05.25\n05.06.25",
        "link": "https://www.service.bund.de/IMPORTE/Ausschreibungen/eVergabe/769931.html;jsessionid=CD71156DCEC286D9D4A6A8D570770280.internet612?nn=4641482&type=0&searchResult=true"
    },
    {
        "title": "Leis\u00adtun\u00adgen zur Lie\u00adfe\u00adrung und Mon\u00adta\u00adge (op\u00adtio\u00adnal) von jagd\u00adli\u00adchen \u2026\nBundesanstalt f\u00fcr Immobilienaufgaben \u2026\n05.05.25\n20.06.25",
        "link": "https://www.service.bund.de/IMPORTE/Ausschreibungen/eVergabe/769889.html;jsessionid=CD71156DCEC286D9D4A6A8D570770280.internet612?nn=4641482&type=0&searchResult=true"
    },
    {
        "title": "Neu\u00adge\u00adstal\u00adtung Schul\u00adhof Se\u00adbas\u00adti\u00adan-Kneipp-Schu\u00adle - Frei\u00adfl\u00e4\u00adchen\u00adge\u00adstal\u00adtung, \u2026\nLandratsamt Unstrut-Hainich-Kreis\n05.05.25\n27.05.25",
        "link": "https://www.service.bund.de/IMPORTE/Ausschreibungen/eVergabe/769104.html;jsessionid=CD71156DCEC286D9D4A6A8D570770280.internet612?nn=4641482&type=0&searchResult=true"
    },
    {
        "title": "Ge\u00admein\u00adde Lind\u00adlar - Di\u00adgi\u00adta\u00adli\u00adsie\u00adrung von Bau\u00adak\u00adten\nGemeinde Lindlar vertreten durch die KoPart eG\n05.05.25\n02.06.25",
        "link": "https://www.service.bund.de/IMPORTE/Ausschreibungen/subreport/2025/05/E73481288.html;jsessionid=CD71156DCEC286D9D4A6A8D570770280.internet612?nn=4641482&type=0&searchResult=true"
    },
    {
        "title": "Be\u00adschaf\u00adfung von feu\u00ader\u00adwehr\u00adtech\u00adni\u00adschen Ge\u00adr\u00e4\u00adten zur Be\u00adla\u00addung ei\u00adnes HLF 10 der \u2026\nVerbandsgemeindeverwaltung Alzey-Land\n05.05.25\n22.05.25",
        "link": "https://www.service.bund.de/IMPORTE/Ausschreibungen/subreport/2025/05/E76697191.html;jsessionid=CD71156DCEC286D9D4A6A8D570770280.internet612?nn=4641482&type=0&searchResult=true"
    },
    {
        "title": "Um\u00adbau und Er\u00adwei\u00adte\u00adrung Feu\u00ader\u00adwehr\u00adge\u00adr\u00e4\u00adtehaus in der Orts\u00adge\u00admein\u00adde Wall\u00adhal\u00adben\nVerbandsgemeindeverwaltung \u2026\n05.05.25\n27.05.25",
        "link": "https://www.service.bund.de/IMPORTE/Ausschreibungen/subreport/2025/05/E63189167.html;jsessionid=CD71156DCEC286D9D4A6A8D570770280.internet612?nn=4641482&type=0&searchResult=true"
    },
    {
        "title": "Um\u00adbau und Er\u00adwei\u00adte\u00adrung Feu\u00ader\u00adwehr\u00adge\u00adr\u00e4\u00adtehaus in der Orts\u00adge\u00admein\u00adde Wall\u00adhal\u00adben\nVerbandsgemeindeverwaltung \u2026\n05.05.25\n27.05.25",
        "link": "https://www.service.bund.de/IMPORTE/Ausschreibungen/subreport/2025/05/E41581788.html;jsessionid=CD71156DCEC286D9D4A6A8D570770280.internet612?nn=4641482&type=0&searchResult=true"
    },
    {
        "title": "Be\u00adschaf\u00adfung PSA f\u00fcr die Frei\u00adwil\u00adli\u00adge Feu\u00ader\u00adwehr Sol\u00adtau\nStadt Soltau(Heidekreis)\n05.05.25\n02.06.25",
        "link": "https://www.service.bund.de/IMPORTE/Ausschreibungen/subreport/2025/05/E19379176.html;jsessionid=CD71156DCEC286D9D4A6A8D570770280.internet612?nn=4641482&type=0&searchResult=true"
    },
    {
        "title": "Ver\u00adga\u00adbe von Un\u00adter\u00adhalts- und Glas\u00adrei\u00adni\u00adgungs\u00adleis\u00adtun\u00adgen der Stadt Schries\u00adheim\nStadt Schriesheim\n05.05.25\n05.06.25",
        "link": "https://www.service.bund.de/IMPORTE/Ausschreibungen/abc/2025/05/401116G327773.html;jsessionid=CD71156DCEC286D9D4A6A8D570770280.internet612?nn=4641482&type=0&searchResult=true"
    },
    {
        "title": "Sa\u00adnie\u00adrung und Er\u00adwei\u00adte\u00adrung der GGS Fus\u00adtern\u00adberg - Schrei\u00adner\u00adar\u00adbei\u00adten M\u00f6\u00adbel II\nZentrale Vergabestelle der Stadt Wesel\n05.05.25\n05.06.25",
        "link": "https://www.service.bund.de/IMPORTE/Ausschreibungen/editor/Stadt-Wesel/2025/05/6027103.html;jsessionid=CD71156DCEC286D9D4A6A8D570770280.internet612?nn=4641482&type=0&searchResult=true"
    },
    {
        "title": "Er\u00adneue\u00adrung der UKW-Sen\u00adder an den BR-Stand\u00adorten Bam\u00adberg, Ho\u00adher Bo\u00adgen, \u2026\nBayerischer Rundfunk A.d.\u00f6.R.\n04.05.25\n03.06.25",
        "link": "https://www.service.bund.de/IMPORTE/Ausschreibungen/dtvp/2025/05/273674.html;jsessionid=CD71156DCEC286D9D4A6A8D570770280.internet612?nn=4641482&type=0&searchResult=true"
    },
    {
        "title": "Lie\u00adfe\u00adrung von B\u00fc\u00adro\u00adbe\u00addarfs\u00adar\u00adti\u00adkeln f\u00fcr den ge\u00adsam\u00adten UV\nProPotsdam GmbH\n04.05.25\n23.05.25",
        "link": "https://www.service.bund.de/IMPORTE/Ausschreibungen/vmp-bb/2025/05/232161.html;jsessionid=CD71156DCEC286D9D4A6A8D570770280.internet612?nn=4641482&type=0&searchResult=true"
    },
    {
        "title": "055-25-00240 - BLB NRW BI / BPol Sankt Au\u00adgus\u00adtin / Neu\u00adbau Sankt Au\u00adgus\u00adtin \u2026\nBau- und Liegenschaftsbetrieb NRW Bielefeld\n04.05.25\n06.06.25",
        "link": "https://www.service.bund.de/IMPORTE/Ausschreibungen/vmp-blb/2025/05/65917.html;jsessionid=CD71156DCEC286D9D4A6A8D570770280.internet612?nn=4641482&type=0&searchResult=true"
    },
    {
        "title": "Hand\u00adwer\u00adker\u00adzeit\u00adver\u00adtrag Dach\u00adde\u00adcker & Klemp\u00adner In\u00adstand\u00adset\u00adzung\nSBH | Schulbau Hamburg\n04.05.25\n23.05.25",
        "link": "https://www.service.bund.de/IMPORTE/Ausschreibungen/healyhudson/2025/05/a1459032-cfd6-4b00-a51a-02d19543ad75.html;jsessionid=CD71156DCEC286D9D4A6A8D570770280.internet612?nn=4641482&type=0&searchResult=true"
    },
    {
        "title": "KH Mer\u00adheim - Bet\u00adten\u00adhaus\u00adsa\u00adnie\u00adrung Haus 20 A-Sei\u00adte Tro\u00adcken\u00adbau\u00adar\u00adbei\u00adten\nKliniken der Stadt K\u00f6ln gGmbH\n04.05.25\n03.06.25",
        "link": "https://www.service.bund.de/IMPORTE/Ausschreibungen/healyhudson/2025/05/6a135e69-6bee-41c5-97dd-3a36bfef2272.html;jsessionid=CD71156DCEC286D9D4A6A8D570770280.internet612?nn=4641482&type=0&searchResult=true"
    },
    {
        "title": "Fern\u00admeld\u00adein\u00adstal\u00adla\u00adti\u00adon, CBF, Geb. 5012, 3.-6.OG\nCharit\u00e9 - Universit\u00e4tsmedizin Berlin\n04.05.25\n05.06.25",
        "link": "https://www.service.bund.de/IMPORTE/Ausschreibungen/vizson/2025/05/02B23EDB50A5957F51304389B7DF113B.html;jsessionid=CD71156DCEC286D9D4A6A8D570770280.internet612?nn=4641482&type=0&searchResult=true"
    },
    {
        "title": "Neu\u00adbau Ret\u00adtungs\u00adwa\u00adche Sch\u00f6n\u00adflie\u00df: Ver\u00adkehrs- und Frei\u00adan\u00adla\u00adgen\u00adpla\u00adnung\nLandkreis Oberhavel\n04.05.25\n04.06.25",
        "link": "https://www.service.bund.de/IMPORTE/Ausschreibungen/vmp-bb/2025/05/231243.html;jsessionid=CD71156DCEC286D9D4A6A8D570770280.internet612?nn=4641482&type=0&searchResult=true"
    },
    {
        "title": "Er\u00adstel\u00adlung Ver\u00admitt\u00adlungs\u00adkon\u00adzept und Aus\u00adstel\u00adlungs\u00adde\u00adsign ein\u00adschlie\u00df\u00adlich \u2026\nLandkreis Dahme-Spreewald\n04.05.25\n02.06.25",
        "link": "https://www.service.bund.de/IMPORTE/Ausschreibungen/vmp-bb/2025/05/232038.html;jsessionid=CD71156DCEC286D9D4A6A8D570770280.internet612?nn=4641482&type=0&searchResult=true"
    },
    {
        "title": "Harks\u00adhei\u00adder Stra\u00ad\u00dfe 70 - Siel\u00adsa\u00adnie\u00adrung\nSBH | Schulbau Hamburg\n04.05.25\n03.06.25",
        "link": "https://www.service.bund.de/IMPORTE/Ausschreibungen/healyhudson/2025/05/e1843aac-62a0-4cc7-99fd-ae364211f40e.html;jsessionid=CD71156DCEC286D9D4A6A8D570770280.internet612?nn=4641482&type=0&searchResult=true"
    },
    {
        "title": "Bill\u00adwer\u00adder Stra\u00ad\u00dfe 31 - Hei\u00adzung Sport\u00adhal\u00adle\nSBH | Schulbau Hamburg\n04.05.25\n03.06.25",
        "link": "https://www.service.bund.de/IMPORTE/Ausschreibungen/healyhudson/2025/05/22558b8d-4852-41bf-afcd-1758d6323f70.html;jsessionid=CD71156DCEC286D9D4A6A8D570770280.internet612?nn=4641482&type=0&searchResult=true"
    },
    {
        "title": "Bun\u00addes\u00ads\u00adtra\u00ad\u00dfe 58 - Prall\u00adwand\nSBH | Schulbau Hamburg\n04.05.25\n03.06.25",
        "link": "https://www.service.bund.de/IMPORTE/Ausschreibungen/healyhudson/2025/05/477167b7-d603-4366-9ae9-b50855a93997.html;jsessionid=CD71156DCEC286D9D4A6A8D570770280.internet612?nn=4641482&type=0&searchResult=true"
    },
    {
        "title": "Eil\u00adbek\u00adtal 35 - Hei\u00adzung\nSBH | Schulbau Hamburg\n04.05.25\n03.06.25",
        "link": "https://www.service.bund.de/IMPORTE/Ausschreibungen/healyhudson/2025/05/58151559-5e54-4c2e-9fc4-dc4b3cfa3c31.html;jsessionid=CD71156DCEC286D9D4A6A8D570770280.internet612?nn=4641482&type=0&searchResult=true"
    },
    {
        "title": "Dienst\u00adleis\u00adtun\u00adgen DA\u00adME\nOberfinanzdirektion Baden-W\u00fcrttemberg - LZfD\n04.05.25\n03.06.25",
        "link": "https://www.service.bund.de/IMPORTE/Ausschreibungen/vmp-bw/2025/05/16361.html;jsessionid=CD71156DCEC286D9D4A6A8D570770280.internet612?nn=4641482&type=0&searchResult=true"
    },
    {
        "title": "De\u00adcken\u00adver\u00adsor\u00adgungs\u00adein\u00adhei\u00adten\nKlinikum St. Marien Amberg\n04.05.25",
        "link": "https://www.service.bund.de/IMPORTE/Ausschreibungen/dtvp/2025/05/273597.html;jsessionid=CD71156DCEC286D9D4A6A8D570770280.internet612?nn=4641482&type=0&searchResult=true"
    },
    {
        "title": "OP-Ti\u00adsche\nKlinikum St. Marien Amberg\n04.05.25",
        "link": "https://www.service.bund.de/IMPORTE/Ausschreibungen/dtvp/2025/05/273605.html;jsessionid=CD71156DCEC286D9D4A6A8D570770280.internet612?nn=4641482&type=0&searchResult=true"
    },
    {
        "title": "OP-Leuch\u00adten\nKlinikum St Marien Amberg\n04.05.25",
        "link": "https://www.service.bund.de/IMPORTE/Ausschreibungen/dtvp/2025/05/273586.html;jsessionid=CD71156DCEC286D9D4A6A8D570770280.internet612?nn=4641482&type=0&searchResult=true"
    },
    {
        "title": "Stadt B\u00fccke\u00adburg - Um\u00adbau, Sa\u00adnie\u00adrung und Er\u00adwei\u00adte\u00adrung Grund\u00adschu\u00adle am Harrl - \u2026\nStadt B\u00fcckeburg\n04.05.25\n02.06.25",
        "link": "https://www.service.bund.de/IMPORTE/Ausschreibungen/dtvp/2025/05/273611.html;jsessionid=CD71156DCEC286D9D4A6A8D570770280.internet612?nn=4641482&type=0&searchResult=true"
    },
    {
        "title": "Ma\u00adna\u00adged Webex 2025\nPostbeamtenkrankenkasse\n04.05.25\n02.06.25",
        "link": "https://www.service.bund.de/IMPORTE/Ausschreibungen/dtvp/2025/05/272779.html;jsessionid=CD71156DCEC286D9D4A6A8D570770280.internet612?nn=4641482&type=0&searchResult=true"
    },
    {
        "title": "Rech\u00adner Hard\u00adware\nUniversit\u00e4tsklinikum Mannheim GmbH\n04.05.25\n02.06.25",
        "link": "https://www.service.bund.de/IMPORTE/Ausschreibungen/vmp-vpbw/2025/05/9091.html;jsessionid=CD71156DCEC286D9D4A6A8D570770280.internet612?nn=4641482&type=0&searchResult=true"
    },
    {
        "title": "P109 - Pla\u00adnung di\u00adver\u00adser Stu\u00adetz\u00adbau\u00adwer\u00adke im Be\u00adreich Ade\u00adnau\u00ader\u00adring in Er\u00adlan\u00adgen\nZweckverband Stadt-Umland-Bahn\n04.05.25\n24.07.25",
        "link": "https://www.service.bund.de/IMPORTE/Ausschreibungen/obb/2025/05/182336.html;jsessionid=CD71156DCEC286D9D4A6A8D570770280.internet612?nn=4641482&type=0&searchResult=true"
    },
    {
        "title": "Sch\u00fc\u00adler\u00adspe\u00adzi\u00adal\u00adbe\u00adf\u00f6r\u00adde\u00adrung zur Lin\u00adden\u00adschu\u00adle - 2 Lo\u00adse\nLandkreis Oberhavel\n04.05.25\n05.06.25",
        "link": "https://www.service.bund.de/IMPORTE/Ausschreibungen/vmp-bb/2025/05/232059.html;jsessionid=CD71156DCEC286D9D4A6A8D570770280.internet612?nn=4641482&type=0&searchResult=true"
    },
    {
        "title": "P108 - Pla\u00adnung di\u00adver\u00adser Stu\u00adetz\u00adbau\u00adwer\u00adke im Be\u00adreich Ten\u00adnen\u00adlo\u00adhe\nZweckverband Stadt-Umland-Bahn\n04.05.25\n22.07.25",
        "link": "https://www.service.bund.de/IMPORTE/Ausschreibungen/obb/2025/05/182335.html;jsessionid=CD71156DCEC286D9D4A6A8D570770280.internet612?nn=4641482&type=0&searchResult=true"
    },
    {
        "title": "Be\u00adreit\u00adstel\u00adlung, Aus\u00adtausch und Auf\u00adbe\u00adrei\u00adtung von Miet\u00adw\u00e4\u00adsche\nMa\u00dfregelvollzugszentrum NIedersachsen\n04.05.25\n03.06.25",
        "link": "https://www.service.bund.de/IMPORTE/Ausschreibungen/vmp-nds/2025/05/114305.html;jsessionid=CD71156DCEC286D9D4A6A8D570770280.internet612?nn=4641482&type=0&searchResult=true"
    },
    {
        "title": "Lie\u00adfe\u00adrung von Wuchs\u00adh\u00fcl\u00adlen f\u00fcr ForstBW\nForst Baden-W\u00fcrttemberg A\u00f6R - Betriebsleitung\n04.05.25\n05.06.25",
        "link": "https://www.service.bund.de/IMPORTE/Ausschreibungen/vmp-bw/2025/05/16360.html;jsessionid=CD71156DCEC286D9D4A6A8D570770280.internet612?nn=4641482&type=0&searchResult=true"
    },
    {
        "title": "VV 24/2025 Pla\u00adnungs\u00adleis\u00adtun\u00adgen zur Er\u00adschlie\u00ad\u00dfung des Kurt-B\u00fcr\u00adger-Sta\u00addi\u00adons, \u2026\nHansestadt Wismar, Rechtsamt\n04.05.25\n11.06.25",
        "link": "https://www.service.bund.de/IMPORTE/Ausschreibungen/vmp-egomv/2025/05/5071.html;jsessionid=CD71156DCEC286D9D4A6A8D570770280.internet612?nn=4641482&type=0&searchResult=true"
    },
    {
        "title": "Pla\u00adnungs\u00adleis\u00adtun\u00adgen f\u00fcr die bar\u00adrie\u00adre\u00adfreie Que\u00adrung der Gleis\u00adan\u00adla\u00adge am Bahn\u00adhof \u2026\nStadtverwaltung Hohen Neuendorf\n04.05.25\n03.06.25",
        "link": "https://www.service.bund.de/IMPORTE/Ausschreibungen/vmp-bb/2025/05/232147.html;jsessionid=CD71156DCEC286D9D4A6A8D570770280.internet612?nn=4641482&type=0&searchResult=true"
    },
    {
        "title": "Lie\u00adfe\u00adrung von Ver\u00adbiss- und Fe\u00adge\u00adschutz f\u00fcr Na\u00addel\u00adholz im Vor\u00adbau f\u00fcr ForstBW\nForst Baden-W\u00fcrttemberg A\u00f6R - Betriebsleitung\n04.05.25\n05.06.25",
        "link": "https://www.service.bund.de/IMPORTE/Ausschreibungen/vmp-bw/2025/05/16359.html;jsessionid=CD71156DCEC286D9D4A6A8D570770280.internet612?nn=4641482&type=0&searchResult=true"
    },
    {
        "title": "Lie\u00adfe\u00adrung von Pflanz- und Fe\u00adge\u00adschutz\u00adst\u00e4\u00adben f\u00fcr ForstBW\nForst Baden-W\u00fcrttemberg A\u00f6R - Betriebsleitung\n04.05.25\n05.06.25",
        "link": "https://www.service.bund.de/IMPORTE/Ausschreibungen/vmp-bw/2025/05/16358.html;jsessionid=CD71156DCEC286D9D4A6A8D570770280.internet612?nn=4641482&type=0&searchResult=true"
    },
    {
        "title": "WA\u00adSAG - Pf\u00f6rt\u00adner\u00adge\u00adb\u00e4u\u00adde - Pla\u00adnung Tech\u00adni\u00adsche Ge\u00adb\u00e4u\u00adde\u00adaus\u00adr\u00fcs\u00adtung (TGA)\nKreis Recklinghausen, Der Landrat\n04.05.25\n02.06.25",
        "link": "https://www.service.bund.de/IMPORTE/Ausschreibungen/vmp-gkd/2025/05/100536.html;jsessionid=CD71156DCEC286D9D4A6A8D570770280.internet612?nn=4641482&type=0&searchResult=true"
    },
    {
        "title": "Tech\u00adni\u00adsche Stra\u00ad\u00dfen\u00adleuch\u00adten f\u00fcr den Ser\u00advice\u00adbe\u00adtrieb \u00d6f\u00adfent\u00adli\u00adcher Raum \u2026\nStadt N\u00fcrnberg - Zentrale Dienste\n04.05.25\n04.06.25",
        "link": "https://www.service.bund.de/IMPORTE/Ausschreibungen/healyhudson/2025/05/972fac31-bde0-4fd9-812d-b01f34ecd4c9.html;jsessionid=CD71156DCEC286D9D4A6A8D570770280.internet612?nn=4641482&type=0&searchResult=true"
    },
    {
        "title": "Bau\u00ad\u00fcber\u00adwa\u00adchung f\u00fcr Haupt\u00adma\u00df\u00adnah\u00adme Ge\u00adne\u00adral\u00adsa\u00adnie\u00adrung 5830 Passau - \u2026\nDB InfraGO AG ? Gesch\u00e4ftsbereich Fahrweg (Bukr 16)\n04.05.25\n02.06.25",
        "link": "https://www.service.bund.de/IMPORTE/Ausschreibungen/healyhudson/2025/05/30b03443-96e5-413d-81f5-ad7f9b1983b9.html;jsessionid=CD71156DCEC286D9D4A6A8D570770280.internet612?nn=4641482&type=0&searchResult=true"
    },
    {
        "title": "BV Um\u00adset\u00adzung des In\u00adte\u00adgrier\u00adten Stadt\u00adteil\u00adent\u00adwick\u00adlungs\u00adkon\u00adzept (ISEK) \u2026\nStadtentwicklungsgesellschaft Recklinghausen mbH\n04.05.25\n05.06.25",
        "link": "https://www.service.bund.de/IMPORTE/Ausschreibungen/vmp-gkd/2025/05/100674.html;jsessionid=CD71156DCEC286D9D4A6A8D570770280.internet612?nn=4641482&type=0&searchResult=true"
    },
    {
        "title": "Lie\u00adfe\u00adrung von Elek\u00adtro\u00adener\u00adgie f\u00fcr den Zeit\u00adraum 2026-2027 nebst \u2026\nGemeinde Wiesenburg/Mark Der B\u00fcrgermeister\n04.05.25\n12.06.25",
        "link": "https://www.service.bund.de/IMPORTE/Ausschreibungen/vmp-bb/2025/05/232033.html;jsessionid=CD71156DCEC286D9D4A6A8D570770280.internet612?nn=4641482&type=0&searchResult=true"
    },
    {
        "title": "Be\u00adschaf\u00adfung von Feu\u00ader\u00adwehr\u00adein\u00adsatz-Ue\u00adber\u00adho\u00adsen der Schutz\u00adstu\u00adfe 2 und \u2026\nStadt Augsburg\n04.05.25\n03.06.25",
        "link": "https://www.service.bund.de/IMPORTE/Ausschreibungen/asp/2025/05/182314.html;jsessionid=CD71156DCEC286D9D4A6A8D570770280.internet612?nn=4641482&type=0&searchResult=true"
    },
    {
        "title": "Rei\u00adni\u00adgungs\u00adleis\u00adtun\u00adgen Gol\u00adzow und Br\u00fcck\nAmt Br\u00fcck, vertretend f\u00fcr die Gemeinde Golzow und \u2026\n04.05.25\n05.06.25",
        "link": "https://www.service.bund.de/IMPORTE/Ausschreibungen/vmp-bb/2025/05/231236.html;jsessionid=CD71156DCEC286D9D4A6A8D570770280.internet612?nn=4641482&type=0&searchResult=true"
    },
    {
        "title": "Durch\u00adf\u00fch\u00adrung von Geldtrans\u00adpor\u00adten -Rah\u00admen\u00adver\u00adein\u00adba\u00adrung-\nMagistrat der Kreisstadt Limburg a. d. Lahn\n04.05.25\n02.06.25",
        "link": "https://www.service.bund.de/IMPORTE/Ausschreibungen/dtvp/2025/05/272940.html;jsessionid=CD71156DCEC286D9D4A6A8D570770280.internet612?nn=4641482&type=0&searchResult=true"
    },
    {
        "title": "Ko\u00adope\u00adra\u00adti\u00adons\u00adschu\u00adle Brau\u00adhaus\u00adstra\u00ad\u00dfe Chem\u00adnitz / Los 02 - Ob\u00adjekt\u00adpla\u00adnung \u2026\nStadt Chemnitz\n04.05.25\n02.06.25",
        "link": "https://www.service.bund.de/IMPORTE/Ausschreibungen/evergabede/2025/05/6605618.html;jsessionid=CD71156DCEC286D9D4A6A8D570770280.internet612?nn=4641482&type=0&searchResult=true"
    },
    {
        "title": "25E30227 - Fi\u00adnanz\u00adamt Sta\u00adde (Am Staats\u00adar\u00adchiv); Neu\u00adbau Fi\u00adnanz\u00adamt Sta\u00adde; \u2026\nLand Niedersachen vertreten durch das Staatliche \u2026\n04.05.25\n06.06.25",
        "link": "https://www.service.bund.de/IMPORTE/Ausschreibungen/vmp-nds/2025/05/114273.html;jsessionid=CD71156DCEC286D9D4A6A8D570770280.internet612?nn=4641482&type=0&searchResult=true"
    },
    {
        "title": "Pan\u00adke Pa13-Pa16 Buch und Po\u00adel\u00adnitz\u00adwie\u00adsen\nSenatsverwaltung fuer Mobilitaet, Verkehr, \u2026\n04.05.25\n17.06.25",
        "link": "https://www.service.bund.de/IMPORTE/Ausschreibungen/svb/2025/05/182304.html;jsessionid=CD71156DCEC286D9D4A6A8D570770280.internet612?nn=4641482&type=0&searchResult=true"
    },
    {
        "title": "UHS - Ge\u00adne\u00adral\u00adsa\u00adnie\u00adrung Lud\u00adwig-Uh\u00adland Schu\u00adle - Schad\u00adstoffsa\u00adnie\u00adrun\u00adgen und \u2026\nStadt N\u00fcrnberg vertreten durch WBG KOMMUNAL GmbH\n04.05.25\n10.06.25",
        "link": "https://www.service.bund.de/IMPORTE/Ausschreibungen/healyhudson/2025/05/c25c1d62-114d-418c-a182-f7d69b3f0d40.html;jsessionid=CD71156DCEC286D9D4A6A8D570770280.internet612?nn=4641482&type=0&searchResult=true"
    },
    {
        "title": "Bau LSW M\u00f6n\u00adchen\u00adglad\u00adbach 1+1b\nDB InfraGO AG ? Gesch\u00e4ftsbereich Fahrweg (Bukr 16)\n04.05.25\n05.06.25",
        "link": "https://www.service.bund.de/IMPORTE/Ausschreibungen/healyhudson/2025/05/6083a9ee-0b0f-4a59-ac80-f09aa13f1cde.html;jsessionid=CD71156DCEC286D9D4A6A8D570770280.internet612?nn=4641482&type=0&searchResult=true"
    },
    {
        "title": "Ge\u00adsamt\u00adschu\u00adle Ro\u00adsen\u00adh\u00f6\u00adhe - Sa\u00adnie\u00adrung SEK I / Ge\u00adr\u00fcst\u00adar\u00adbei\u00adten\nStadt Bielefeld - Amt f\u00fcr Zentrale Leistungen\n04.05.25\n05.06.25",
        "link": "https://www.service.bund.de/IMPORTE/Ausschreibungen/vmp-westfalen/2025/05/49772107.html;jsessionid=CD71156DCEC286D9D4A6A8D570770280.internet612?nn=4641482&type=0&searchResult=true"
    },
    {
        "title": "LB084 Ab\u00adbruch\u00adar\u00adbei\u00adten Alt\u00adbau mit An\u00adbau I Mu\u00adsik\u00adschu\u00adle T\u00fc\u00adbin\u00adgen\nUniversit\u00e4tsstadt T\u00fcbingen - Zentrale \u2026\n04.05.25\n11.06.25",
        "link": "https://www.service.bund.de/IMPORTE/Ausschreibungen/vmp-vpbw/2025/05/9088.html;jsessionid=CD71156DCEC286D9D4A6A8D570770280.internet612?nn=4641482&type=0&searchResult=true"
    },
    {
        "title": "Bun\u00addes\u00adstadt Bonn, Sch\u00fc\u00adler\u00adbe\u00adf\u00f6r\u00adde\u00adrung 2025-2027 (Mit der Op\u00adti\u00adon der \u2026\nBundesstadt Bonn - Referat Vergabedienste\n04.05.25\n03.06.25",
        "link": "https://www.service.bund.de/IMPORTE/Ausschreibungen/vmp-mebit/2025/05/82572.html;jsessionid=CD71156DCEC286D9D4A6A8D570770280.internet612?nn=4641482&type=0&searchResult=true"
    },
    {
        "title": "LWL - F\u00f6r\u00adder\u00adschu\u00adle - Rhein.-Westf. Re\u00adal\u00adschu\u00adle , F\u00f6r\u00adder\u00adschwer\u00adpunkt, \u2026\nLWL - Bau- und Liegenschaftsbetrieb (LWL-BLB)\n04.05.25\n03.06.25",
        "link": "https://www.service.bund.de/IMPORTE/Ausschreibungen/vmp-westfalen/2025/05/49819585.html;jsessionid=CD71156DCEC286D9D4A6A8D570770280.internet612?nn=4641482&type=0&searchResult=true"
    },
    {
        "title": "Rah\u00admen\u00adver\u00adein\u00adba\u00adrung \u00fcber die Lie\u00adfe\u00adrung von Re\u00adcy\u00adcling\u00adko\u00adpier\u00adpa\u00adpier f\u00fcr die \u2026\nStadt Hamm, Vermessungs- und Katasteramt\n04.05.25\n10.06.25",
        "link": "https://www.service.bund.de/IMPORTE/Ausschreibungen/vmp-gkd/2025/05/100637.html;jsessionid=CD71156DCEC286D9D4A6A8D570770280.internet612?nn=4641482&type=0&searchResult=true"
    },
    {
        "title": "Ma\u00adna\u00adged Print Ser\u00advice / Dru\u00adcker\nStadt Wiehl\n04.05.25\n10.06.25",
        "link": "https://www.service.bund.de/IMPORTE/Ausschreibungen/vmp-mebit/2025/05/83095.html;jsessionid=CD71156DCEC286D9D4A6A8D570770280.internet612?nn=4641482&type=0&searchResult=true"
    },
    {
        "title": "Stadt Wei\u00adkers\u00adheim, Sa\u00adnie\u00adrung Hal\u00adlen\u00adbad, BA 1, Los 7 Me\u00adtall\u00adbau\u00adar\u00adbei\u00adten, \u2026\nStadt Weikersheim\n04.05.25\n06.06.25",
        "link": "https://www.service.bund.de/IMPORTE/Ausschreibungen/dtvp/2025/05/273541.html;jsessionid=CD71156DCEC286D9D4A6A8D570770280.internet612?nn=4641482&type=0&searchResult=true"
    },
    {
        "title": "2418 In\u00adnen\u00adaus\u00adbau Schwarz\u00adbau: Pla\u00adnung KG 440/450\nTechnische Universit\u00e4t Braunschweig Abteilung 39\n03.05.25\n02.06.25",
        "link": "https://www.service.bund.de/IMPORTE/Ausschreibungen/vmp-nds/2025/05/114253.html;jsessionid=CD71156DCEC286D9D4A6A8D570770280.internet612?nn=4641482&type=0&searchResult=true"
    },
    {
        "title": "Lie\u00adfe\u00adrung von Kon\u00adden\u00adsa\u00adtor-An\u00adsteck\u00admi\u00adkro\u00adfo\u00adne\nStiftung Staatstheater N\u00fcrnberg\n03.05.25\n12.05.25",
        "link": "https://www.service.bund.de/IMPORTE/Ausschreibungen/healyhudson/2025/05/a0c9a711-fc37-4579-85c2-16a083229182.html;jsessionid=CD71156DCEC286D9D4A6A8D570770280.internet612?nn=4641482&type=0&searchResult=true"
    },
    {
        "title": "FG1213 FMIT, Elek\u00adtro\nUniversit\u00e4tsklinikum Halle (Saale)\n03.05.25\n06.06.25",
        "link": "https://www.service.bund.de/IMPORTE/Ausschreibungen/evergabede/2025/05/6604020.html;jsessionid=CD71156DCEC286D9D4A6A8D570770280.internet612?nn=4641482&type=0&searchResult=true"
    },
    {
        "title": "Bau ei\u00adner Kl\u00e4r\u00adschlamm\u00adfau\u00adlung mit Faul\u00adbe\u00adh\u00e4l\u00adter ZKA Sils\u00adtedt - LOS 2 Tief- \u2026\nStadt Halberstadt\n03.05.25\n02.06.25",
        "link": "https://www.service.bund.de/IMPORTE/Ausschreibungen/evergabede/2025/05/6604098.html;jsessionid=CD71156DCEC286D9D4A6A8D570770280.internet612?nn=4641482&type=0&searchResult=true"
    },
    {
        "title": "FG1213_ELT, Stark\u00adstrom\nUniversit\u00e4tsklinikum Halle (Saale)\n03.05.25\n06.06.25",
        "link": "https://www.service.bund.de/IMPORTE/Ausschreibungen/evergabede/2025/05/6603753.html;jsessionid=CD71156DCEC286D9D4A6A8D570770280.internet612?nn=4641482&type=0&searchResult=true"
    },
    {
        "title": "Neu\u00adbau ei\u00adner in\u00adte\u00adgrier\u00adten Leit\u00adstel\u00adle - Los 16 - Flucht\u00adtrep\u00adpe\nLandkreis Anhalt-Bitterfeld\n03.05.25\n20.05.25",
        "link": "https://www.service.bund.de/IMPORTE/Ausschreibungen/evergabede/2025/05/6603732.html;jsessionid=CD71156DCEC286D9D4A6A8D570770280.internet612?nn=4641482&type=0&searchResult=true"
    },
    {
        "title": "Lie\u00adfe\u00adrung ver\u00adschie\u00adde\u00adner IT-Hard\u00adware\nLandkreis Eichsfeld - Zentrale Vergabestelle\n03.05.25\n02.06.25",
        "link": "https://www.service.bund.de/IMPORTE/Ausschreibungen/evergabede/2025/05/6604044.html;jsessionid=CD71156DCEC286D9D4A6A8D570770280.internet612?nn=4641482&type=0&searchResult=true"
    },
    {
        "title": "Pla\u00adnungs\u00adleis\u00adtun\u00adgen ALG 6 FA, BBS2 An\u00adbau Er\u00adwei\u00adte\u00adrung\nRegion Hannover\n03.05.25\n03.06.25",
        "link": "https://www.service.bund.de/IMPORTE/Ausschreibungen/evergabede/2025/05/6603711.html;jsessionid=CD71156DCEC286D9D4A6A8D570770280.internet612?nn=4641482&type=0&searchResult=true"
    },
    {
        "title": "L\u00fctz\u00adner Str., VE01: Gleis-, Lei\u00adtungs- und Stra\u00ad\u00dfen\u00adbau\nLeipziger Verkehrsbetriebe (LVB) GmbH\n03.05.25\n04.06.25",
        "link": "https://www.service.bund.de/IMPORTE/Ausschreibungen/evergabede/2025/05/6603922.html;jsessionid=CD71156DCEC286D9D4A6A8D570770280.internet612?nn=4641482&type=0&searchResult=true"
    },
    {
        "title": "Bal\u00adduin\u00adbr\u00fccke_Fest\u00adhal\u00adte\u00adpunk\u00adte Kap\u00adpe\nStadt Koblenz\n03.05.25\n21.05.25",
        "link": "https://www.service.bund.de/IMPORTE/Ausschreibungen/rlp-komm/2025/05/15505.html;jsessionid=CD71156DCEC286D9D4A6A8D570770280.internet612?nn=4641482&type=0&searchResult=true"
    },
    {
        "title": "Char\u00adlot\u00adten\u00adbur\u00adger Stra\u00ad\u00dfe 84 - Siel\u00adsa\u00adnie\u00adrung\nSBH | Schulbau Hamburg\n03.05.25\n03.06.25",
        "link": "https://www.service.bund.de/IMPORTE/Ausschreibungen/healyhudson/2025/05/22d14113-79ae-4cdc-9467-2bfc2e7caf9d.html;jsessionid=CD71156DCEC286D9D4A6A8D570770280.internet612?nn=4641482&type=0&searchResult=true"
    },
    {
        "title": "Bun\u00addes\u00adstadt Bonn, Neu\u00adge\u00adstal\u00adtung Rhei\u00adnu\u00adfer\u00adpro\u00adme\u00adna\u00adde 2.BA - Sta\u00adtik \u2026\nBundesstadt Bonn - Referat Vergabedienste\n03.05.25\n03.06.25",
        "link": "https://www.service.bund.de/IMPORTE/Ausschreibungen/vmp-mebit/2025/05/83194.html;jsessionid=CD71156DCEC286D9D4A6A8D570770280.internet612?nn=4641482&type=0&searchResult=true"
    },
    {
        "title": "Neu\u00adbau FWGH Fur\u00adpach - Ar\u00adchi\u00adtek\u00adten\u00adleis\u00adtun\u00adgen\nStadt Neunkirchen\n03.05.25\n03.06.25",
        "link": "https://www.service.bund.de/IMPORTE/Ausschreibungen/abc/2025/05/401017G327704.html;jsessionid=CD71156DCEC286D9D4A6A8D570770280.internet612?nn=4641482&type=0&searchResult=true"
    },
    {
        "title": "Rah\u00admen\u00adver\u00adein\u00adba\u00adrung - Pr\u00fc\u00adfung/War\u00adtung von Feu\u00ader\u00adl\u00f6\u00adschern, Wand\u00adhy\u00addran\u00adten und \u2026\nUniversit\u00e4t des Saarlandes\n03.05.25\n30.05.25",
        "link": "https://www.service.bund.de/IMPORTE/Ausschreibungen/abc/2025/05/400805G327557.html;jsessionid=CD71156DCEC286D9D4A6A8D570770280.internet612?nn=4641482&type=0&searchResult=true"
    },
    {
        "title": "ABS 2025.04 Mit\u00adtags\u00adver\u00adpfle\u00adgung an sechs Ganz\u00adta\u00adges\u00adschu\u00adlen und ei\u00adner \u2026\nStadt Pforzheim\n03.05.25\n02.06.25",
        "link": "https://www.service.bund.de/IMPORTE/Ausschreibungen/abc/2025/05/400666G327455.html;jsessionid=CD71156DCEC286D9D4A6A8D570770280.internet612?nn=4641482&type=0&searchResult=true"
    },
    {
        "title": "Rah\u00admen\u00adver\u00adtrag Be\u00adwa\u00adchung f\u00fcr das Mu\u00adse\u00adum Ber\u00adlin-Karls\u00adhorst e.V.\nStiftung Deutsches Historisches Museum\n03.05.25",
        "link": "https://www.service.bund.de/IMPORTE/Ausschreibungen/eVergabe/769640.html;jsessionid=CD71156DCEC286D9D4A6A8D570770280.internet612?nn=4641482&type=0&searchResult=true"
    },
    {
        "title": "Elek\u00adtro\u00adin\u00adstal\u00adla\u00adti\u00adon Pho\u00adto\u00advol\u00adtaik\u00adan\u00adla\u00adge auf dem Funk\u00adti\u00adons\u00adge\u00adb\u00e4u\u00adde\nTh\u00fcringer Landesamt f\u00fcr Bau und Verkehr, Hochbau \u2026\n03.05.25\n12.06.25",
        "link": "https://www.service.bund.de/IMPORTE/Ausschreibungen/eVergabe/769702.html;jsessionid=CD71156DCEC286D9D4A6A8D570770280.internet612?nn=4641482&type=0&searchResult=true"
    },
    {
        "title": "Dach\u00adde\u00adcker- und Klemp\u00adner\u00adar\u00adbei\u00adten - Ener\u00adge\u00adti\u00adsche Dachsa\u00adnie\u00adrung am \u2026\nStadt M\u00fcnster - Zentrale Rechtsdienstleistungen \u2026\n03.05.25",
        "link": "https://www.service.bund.de/IMPORTE/Ausschreibungen/vmp-westfalen/2025/05/49852606.html;jsessionid=CD71156DCEC286D9D4A6A8D570770280.internet612?nn=4641482&type=0&searchResult=true"
    },
    {
        "title": "Rhein Wied Sta\u00addi\u00adon Neu\u00adwied - Aus\u00adtausch der Ra\u00adsen\u00adsport\u00adfl\u00e4\u00adche\nStadtverwaltung Neuwied\n03.05.25\n27.05.25",
        "link": "https://www.service.bund.de/IMPORTE/Ausschreibungen/subreport/2025/05/E92863169.html;jsessionid=CD71156DCEC286D9D4A6A8D570770280.internet612?nn=4641482&type=0&searchResult=true"
    },
    {
        "title": "In\u00adter\u00ades\u00adsen\u00adbe\u00adkun\u00addungs\u00adver\u00adfah\u00adren ge\u00adm\u00e4\u00df \u00a7 26 Sekt\u00adVO\nStadtwerke-Nordhausen-Gruppe\n03.05.25",
        "link": "https://www.service.bund.de/IMPORTE/Ausschreibungen/eVergabe/766468.html;jsessionid=CD71156DCEC286D9D4A6A8D570770280.internet612?nn=4641482&type=0&searchResult=true"
    },
    {
        "title": "War\u00adtungs\u00adar\u00adbei\u00adten an den Br\u00fccken\u00adbe\u00adsich\u00adti\u00adgungs\u00adwa\u00adgen der Br\u00fccke \u00fcber den \u2026\nStadt Neuss, der B\u00fcrgermeister\n03.05.25\n20.05.25",
        "link": "https://www.service.bund.de/IMPORTE/Ausschreibungen/subreport/2025/05/E23128811.html;jsessionid=CD71156DCEC286D9D4A6A8D570770280.internet612?nn=4641482&type=0&searchResult=true"
    },
    {
        "title": "Um\u00adstel\u00adlung Atem\u00adschutz auf \u00dcber\u00addruck\nVerbandsgemeinde Pellenz\n03.05.25\n22.05.25",
        "link": "https://www.service.bund.de/IMPORTE/Ausschreibungen/subreport/2025/05/E72744171.html;jsessionid=CD71156DCEC286D9D4A6A8D570770280.internet612?nn=4641482&type=0&searchResult=true"
    },
    {
        "title": "Stra\u00ad\u00dfe\u00adner\u00adneue\u00adrung Lan\u00adge Stra\u00ad\u00dfe, von Su\u00adle\u00adbr\u00fccke bis Kir\u00adchen\u00adkreu\u00adzung\nStadt Sulingen (LK Diepholz)\n03.05.25\n20.05.25",
        "link": "https://www.service.bund.de/IMPORTE/Ausschreibungen/subreport/2025/05/E98131765.html;jsessionid=CD71156DCEC286D9D4A6A8D570770280.internet612?nn=4641482&type=0&searchResult=true"
    },
    {
        "title": "Ab\u00adwas\u00adser\u00adwerk Mai\u00adfeld - Ka\u00adnal\u00adsa\u00adnie\u00adrung in der OG Mert\u00adloch\nVerbandsgemeindeverwaltung Maifeld -Zentrale \u2026\n03.05.25\n04.06.25",
        "link": "https://www.service.bund.de/IMPORTE/Ausschreibungen/subreport/2025/05/E21514337.html;jsessionid=CD71156DCEC286D9D4A6A8D570770280.internet612?nn=4641482&type=0&searchResult=true"
    },
    {
        "title": "Er\u00adstel\u00adlung ei\u00adnes Kli\u00adma\u00adschutz\u00adkon\u00adzep\u00adtes f\u00fcr die Ver\u00adwal\u00adtung des Land\u00adkrei\u00adses \u2026\nLandkreis Cuxhaven\n03.05.25\n27.05.25",
        "link": "https://www.service.bund.de/IMPORTE/Ausschreibungen/subreport/2025/05/E67831185.html;jsessionid=CD71156DCEC286D9D4A6A8D570770280.internet612?nn=4641482&type=0&searchResult=true"
    },
    {
        "title": "Ge\u00adwerb\u00adli\u00adche Schu\u00adlen Do\u00adnaue\u00adschin\u00adgen, Sa\u00adnie\u00adrung der Turn- und Sport\u00adhal\u00adle, \u2026\nLandratsamt Schwarzwald-Baar-Kreis\n03.05.25\n28.05.25",
        "link": "https://www.service.bund.de/IMPORTE/Ausschreibungen/subreport/2025/05/E88337278.html;jsessionid=CD71156DCEC286D9D4A6A8D570770280.internet612?nn=4641482&type=0&searchResult=true"
    },
    {
        "title": "Wacht\u00adhaus Sa\u00adnie\u00adrung\nStadtverwaltung Kirchheim unter Teck\n03.05.25\n21.05.25",
        "link": "https://www.service.bund.de/IMPORTE/Ausschreibungen/subreport/2025/05/E14126825.html;jsessionid=CD71156DCEC286D9D4A6A8D570770280.internet612?nn=4641482&type=0&searchResult=true"
    },
    {
        "title": "Ka\u00adnal- und Was\u00adser\u00adlei\u00adtungs\u00adbau\u00adar\u00adbei\u00adten in Win\u00adden, Schul\u00adstra\u00ad\u00dfe\nVerbandsgemeindeverwaltung Bad Ems - Nassau\n03.05.25\n22.05.25",
        "link": "https://www.service.bund.de/IMPORTE/Ausschreibungen/subreport/2025/05/E13949117.html;jsessionid=CD71156DCEC286D9D4A6A8D570770280.internet612?nn=4641482&type=0&searchResult=true"
    }
]